README.rst
gallows.py
setup.py
gallows.egg-info/PKG-INFO
gallows.egg-info/SOURCES.txt
gallows.egg-info/dependency_links.txt
gallows.egg-info/requires.txt
gallows.egg-info/top_level.txt