Metadata-Version: 1.1
Name: gallows
Version: 0.6.0
Summary: The word game Hangman based on 'Invent Your Own Computer Games with Python'.
Home-page: http://github.com/chennaipy/hangman
Author: Vijay Kumar B.
Author-email: vijaykumar@bravegnu.org
License: BSD 2-Clause
Platform: UNKNOWN
Classifier: Development Status :: 5 - Production/Stable
Classifier: Environment :: Console
Classifier: Intended Audience :: End Users/Desktop
Classifier: Intended Audience :: Education
Classifier: License :: OSI Approved :: BSD License
Classifier: Natural Language :: English
Classifier: Operating System :: MacOS :: MacOS X
Classifier: Operating System :: Microsoft :: Windows
Classifier: Operating System :: POSIX
Classifier: Programming Language :: Python :: 2.6
Classifier: Programming Language :: Python :: 2.7
Classifier: Programming Language :: Python :: 3.2
Classifier: Programming Language :: Python :: 3.3
Classifier: Programming Language :: Python :: 3.4
Classifier: Topic :: Games/Entertainment :: Puzzle Games
